{
  "parent": "minecraft:recipes/root",
  "rewards": {
    "recipes": [
      "super_block_world:smooth_royalite"
    ]
  },
  "criteria": {
    "has_material": {
      "trigger": "minecraft:inventory_changed",
      "conditions": {
        "items": [
          {
            "items": [
              "super_block_world:royalite"
            ]
          }
        ]
      }
    },
    "has_the_recipe": {
      "trigger": "minecraft:recipe_unlocked",
      "conditions": {
        "recipe": "super_block_world:smooth_royalite"
      }
    }
  },
  "requirements": [
    [
      "has_material",
      "has_the_recipe"
    ]
  ]
}